pepitatools/__init__.py
pepitatools/absolute.py
pepitatools/analyze.py
pepitatools/configuration.py
pepitatools/dose_response.py
pepitatools/imagej_scripts.py
pepitatools/imageops.py
pepitatools/infection.py
pepitatools/interactions.py
pepitatools/keyence.py
pepitatools/pipeline.py
pepitatools/utils.py
pepitatools/data/OpenForMasking.ijm
pepitatools/data/OpenForMaskingSingle.ijm
pepitatools/data/SaveFishMask.ijm
pepitatools/data/SaveFishNullMask.ijm
pepitatools/data/__init__.py
pepitatools/data/keyence_BZX800_lenses.csv
pepitatools/data/macroize.sh
pepitatools/data/neo_data.csv
pepitatools/scripts/__init__.py
pepitatools/scripts/pepita_cli.py
PEPITA_tools-0.1.2.dist-info/LICENSE
PEPITA_tools-0.1.2.dist-info/METADATA
PEPITA_tools-0.1.2.dist-info/WHEEL
PEPITA_tools-0.1.2.dist-info/entry_points.txt
PEPITA_tools-0.1.2.dist-info/top_level.txt
PEPITA_tools-0.1.2.dist-info/RECORD
