Metadata-Version: 2.1
Name: PEPITA-tools
Version: 0.1.2
Summary: Pipeline for quantifying hair cell health in whole-zebrafish images.
Author: Ethan Bustad
Maintainer: Ethan Bustad, Braden Griebel
Project-URL: Repository, https://github.com/Ma-Lab-Seattle-Childrens-CGIDR/PEPITA-tools
Project-URL: Homepage, https://www.seattlechildrens.org/research/centers-programs/global-infectious-disease-research/research-areas-and-labs/ma-lab/
Project-URL: Issues, https://github.com/Ma-Lab-Seattle-Childrens-CGIDR/PEPITA-tools/issues
Keywords: Zebrafish,Haircell,Antibiotic,Ototoxicity
Requires-Python: >=3.9
License-File: LICENSE
Requires-Dist: imagecodecs>=2024.9.22
Requires-Dist: matplotlib>=3.9.2
Requires-Dist: numpy>=2.0.2
Requires-Dist: opencv-python>=4.10.0.84
Requires-Dist: pandas>=2.2.3
Requires-Dist: pytest>=8.3.3
Requires-Dist: scikit-image>=0.18
Requires-Dist: scipy>=1.13.1
Requires-Dist: seaborn>=0.13.2
Requires-Dist: xlsxwriter>=3.2.0
